Metadata-Version: 2.1
Name: tailread
Version: 1.0.2
Summary: A Simple line generator from tail of file
Home-page: https://github.com/zwolf21/tailread
Author: HS Moon
Author-email: pbr112@naver.com
License: MIT
Keywords: tail,python tail,tailread
Platform: UNKNOWN
Classifier: Programming Language :: Python :: 3.4
Classifier: Programming Language :: Python :: 3.5
Classifier: Programming Language :: Python :: 3.6
Classifier: Programming Language :: Python :: 3.7
Classifier: Programming Language :: Python :: 3.8
Classifier: Programming Language :: Python :: 3.9
Classifier: Programming Language :: Python :: 3.10
Requires-Python: >=3.4
